models/__init__.py
models/admin.py
models/assess.py
models/base.py
models/cache.py
models/dashboard.py
models/product.py
models/report.py
models/types.py
taranis_models-1.2.4.dist-info/licenses/LICENSE.md
taranis_models-1.2.4.dist-info/METADATA
taranis_models-1.2.4.dist-info/WHEEL
taranis_models-1.2.4.dist-info/top_level.txt
taranis_models-1.2.4.dist-info/RECORD
