Metadata-Version: 2.4
Name: taranis-models
Version: 1.2.4
Summary: Taranis AI Models
Maintainer-email: AIT <benjamin.akhras@ait.ac.at>
License-Expression: EUPL-1.2
Project-URL: Source Code, https://github.com/taranis-ai/taranis-ai
Classifier: Programming Language :: Python
Classifier: Programming Language :: Python :: 3
Classifier: Programming Language :: Python :: 3.12
Classifier: Framework :: Flask
Classifier: Topic :: Security
Requires-Python: >=3.12
License-File: LICENSE.md
Requires-Dist: pydantic
Requires-Dist: pydantic-settings
Requires-Dist: python-dotenv
Requires-Dist: langcodes
Provides-Extra: dev
Requires-Dist: ruff; extra == "dev"
Requires-Dist: pytest; extra == "dev"
Requires-Dist: wheel; extra == "dev"
Dynamic: license-file
